arrow_table_dict_conversion.py
arrow_table_dict_conversion-0.1.3.dist-info/LICENSE
arrow_table_dict_conversion-0.1.3.dist-info/METADATA
arrow_table_dict_conversion-0.1.3.dist-info/WHEEL
arrow_table_dict_conversion-0.1.3.dist-info/RECORD
