Metadata-Version: 2.3
Name: arrow-table-dict-conversion
Version: 0.1.3
Summary: 
License: MIT
Author: Jingheng_Huang
Author-email: huangjh233@outlook.com
Requires-Python: >=3.12
Classifier: Programming Language :: Python :: 3
Classifier: Operating System :: OS Independent
Requires-Dist: pyarrow (>=0.16.0)
